stactools/drcog_lulc/__init__.py
stactools/drcog_lulc/commands.py
stactools/drcog_lulc/constants.py
stactools/drcog_lulc/stac.py
stactools/drcog_lulc/tile.py
stactools_drcog_lulc-0.2.0.dist-info/LICENSE
stactools_drcog_lulc-0.2.0.dist-info/METADATA
stactools_drcog_lulc-0.2.0.dist-info/WHEEL
stactools_drcog_lulc-0.2.0.dist-info/top_level.txt
stactools_drcog_lulc-0.2.0.dist-info/RECORD
