Metadata-Version: 2.1
Name: stactools-drcog-lulc
Version: 0.2.0
Summary: stactools package for Denver Regional Council of Governments (DRCOG) Land Use Land Cover (LULC)
Home-page: https://github.com/stactools-packages/drcog-lulc
Author: Paola Holleway
Author-email: paolaholleway@gmail.com
Project-URL: Issues, https://github.com/stactools-packages/drcog-lulc/issues
Keywords: stactools,pystac,catalog,STAC,landcover
Classifier: Development Status :: 4 - Beta
Classifier: License :: OSI Approved :: Apache Software License
Classifier: Programming Language :: Python :: 3.7
Classifier: Programming Language :: Python :: 3.8
Classifier: Programming Language :: Python :: 3.9
License-File: LICENSE
Requires-Dist: stactools (>=0.2.6)
